04_spi-master/rom.v
module rom (
  input wire clk,

  // プログラムが 4K(0〜4095) 命令以内に収まる前提で、それ以上のアドレスは指さない。
  // 足りなくなったら後で拡張する。
  input wire [11:0] addr,
  output reg [15:0] instruction
);

  reg [15:0] mem [4095:0];

  initial begin
    $readmemb("test.hack", mem);
  end

  always @(posedge clk) begin
    instruction <= mem[addr];
  end

endmodule

04_spi-master/rom_tb.v
module rom_tb;

  reg         clk;
  reg  [11:0] addr;
  wire [15:0] instruction;

  rom dut (
    .clk(clk),
    .addr(addr),
    .instruction(instruction)
  );

  initial clk = 0;
  always #5 clk = ~clk; // 5単位ごとに反転

  initial begin
    $dumpfile("rom_tb.vcd");
    $dumpvars(0, rom_tb);

    // 初期値
    addr = 0;

    // テスト1: addr = 0 にして、1サイクル待つ
    #10;
    $display("addr=%d, inst=%h", addr, instruction);

    addr = 1;
    #10;
    $display("addr=%d, inst=%h", addr, instruction);

    addr = 2;
    #10;
    $display("addr=%d, inst=%h", addr, instruction);

    addr = 3;
    #10;
    $display("addr=%d, inst=%h", addr, instruction);

    $finish;
  end

endmodule

04_spi-master/rom_tb.vcd
$date
	Sat May 23 13:47:43 2026
$end
$version
	Icarus Verilog
$end
$timescale
	1s
$end
$scope module rom_tb $end
$var wire 16 ! instruction [15:0] $end
$var reg 12 " addr [11:0] $end
$var reg 1 # clk $end
$scope module dut $end
$var wire 12 $ addr [11:0] $end
$var wire 1 # clk $end
$var reg 16 % instruction [15:0] $end
$upscope $end
$upscope $end
$enddefinitions $end
$comment Show the parameter values. $end
$dumpall
$end
#0
$dumpvars
bx %
b0 $
0#
b0 "
bx !
$end
#5
b111 !
b111 %
1#
#10
0#
b1 "
b1 $
#15
b1110110000010000 !
b1110110000010000 %
1#
#20
0#
b10 "
b10 $
#25
b0 !
b0 %
1#
#30
0#
b11 "
b11 $
#35
b1110001100001000 !
b1110001100001000 %
1#
