04_spi-master/spi_master.v
`default_nettype none

module spi_master (
    input  wire        clk,
    input  wire        rst_n,
    input  wire        start,
    input  wire [7:0]  data_in,
    output reg         sclk,
    output reg         mosi,
    output reg         cs,
    output reg         busy
);

  // SCLK の半周期 = clk 何サイクル分か
  parameter SCLK_HALF = 4;

  // 状態の定義
  localparam IDLE       = 2'd0;
  localparam SHIFT_LOW  = 2'd1;
  localparam SHIFT_HIGH = 2'd2;
  localparam DONE       = 2'd3;

  // 内部状態
  reg [1:0] state;
  reg [2:0] bit_count;
  reg [3:0] clk_count;
  reg [7:0] shift_reg;

  // メイン回路
  always @(posedge clk or negedge rst_n) begin
    if (!rst_n) begin

      // ============================
      // ここに「リセット時の初期化」を書く
      // 全部の reg を安全な値にする
      // ============================
      sclk      <= 1'b0;
      mosi      <= 1'b0;
      cs        <= 1'b1;
      busy      <= 1'b0;
      state     <= IDLE;
      bit_count <= 3'b000;
      clk_count <= 4'b0000;
      shift_reg <= 8'b0000_0000;

    end else begin
      case (state)
        IDLE: begin
          // ============================
          // 待機中。何もしない、cs=High, sclk=Low
          // start が来たら、shift_regにdata_inをロードして、
          //   SHIFT_LOWに遷移、mosi=data_in[7], cs=Low, busy=1
          // ============================
          cs   <= 1'b1;
          sclk <= 1'b0;
          busy <= 1'b0;

          if (start == 1) begin
            state     <= SHIFT_LOW;
            cs        <= 1'b0;
            busy      <= 1'b1;
            shift_reg <= data_in;
            mosi      <= data_in[7];
            bit_count <= 3'b000;
            clk_count <= 4'b0000;
          end
        end
        
        SHIFT_LOW: begin
          // ============================
          // sclk=Low の状態。clk_countを数える。
          // clk_count == SCLK_HALF-1 になったら SHIFT_HIGHに遷移
          // ============================
          if (clk_count == SCLK_HALF - 1) begin
            state     <= SHIFT_HIGH;
            clk_count <= 4'b0000;
            sclk      <= 1'b1;
          end else begin
            clk_count <= clk_count + 1;
          end
        end

        SHIFT_HIGH: begin
          // ============================
          // sclk=High の状態。clk_countを数える。
          // clk_count == SCLK_HALF-1 になったら、
          //   - bit_count == 7 なら DONE に遷移
          //   - そうでなければ SHIFT_LOW に戻り、bit_countを+1、shift_regをシフト、mosi更新
          // ============================
          if (clk_count == SCLK_HALF - 1) begin
            clk_count <= 4'b0000;
            sclk      <= 1'b0;

            if (bit_count == 7) begin
              state     <= DONE;
            end else begin
              state     <= SHIFT_LOW;
              bit_count <= bit_count + 1;
              shift_reg <= {shift_reg[6:0], 1'b0};
              mosi      <= shift_reg[6];   
            end
          end else begin
            clk_count <= clk_count + 1;
          end
        end

        DONE: begin
          // ============================
          // cs=High, busy=0 にして IDLEへ戻る
          // ============================
          cs    <= 1'b1;
          busy  <= 1'b0;
          state <= IDLE;
        end
      endcase
    end
  end

endmodule

04_spi-master/spi_master_tb.v
`timescale 1ns/1ps

module spi_master_tb;

  // テストベンチ内で使う信号
  reg        clk;
  reg        rst_n;
  reg        start;
  reg [7:0]  data_in;
  wire       sclk;
  wire       mosi;
  wire       cs;
  wire       busy;

  // テスト対象のモジュールをインスタンス化
  spi_master u_dut (
    .clk     (clk),
    .rst_n   (rst_n),
    .start   (start),
    .data_in (data_in),
    .sclk    (sclk),
    .mosi    (mosi),
    .cs      (cs),
    .busy    (busy)
  );

  // クロック生成: 5ns周期 → 200MHz相当(シミュレーション用なので速度は適当)
  initial clk = 0;
  always #5 clk = ~clk;

  // テストシナリオ
  initial begin
    // 波形を保存するための設定
    $dumpfile("spi_master.vcd");
    $dumpvars(0, spi_master_tb);

    // 信号を初期化する
    rst_n   = 0;
    start   = 0;
    data_in = 8'b0000_0000;

    // 少し待つ
    #20;

    // rst_nを1にしてリセット解除
    rst_n = 1;

    // もう少し待つ
    #20;

    // data_inに 0xAA をセット
    data_in = 8'b1010_1010;

    //  start を1にして1サイクル後に0に戻す
    start = 1;
    #10;
    start = 0;

    // busyが0に戻るまで待つ(送信完了まで)
    wait (busy == 0);
    #50;

    // ↓ シミュレーション終了
    $finish;
  end

endmodule

04_spi-master/spi_master.vcd
$date
	Mon May  4 21:34:03 2026
$end
$version
	Icarus Verilog
$end
$timescale
	1ps
$end
$scope module spi_master_tb $end
$var wire 1 ! sclk $end
$var wire 1 " mosi $end
$var wire 1 # cs $end
$var wire 1 $ busy $end
$var reg 1 % clk $end
$var reg 8 & data_in [7:0] $end
$var reg 1 ' rst_n $end
$var reg 1 ( start $end
$scope module u_dut $end
$var wire 1 % clk $end
$var wire 8 ) data_in [7:0] $end
$var wire 1 ' rst_n $end
$var wire 1 ( start $end
$var parameter 2 * DONE $end
$var parameter 2 + IDLE $end
$var parameter 32 , SCLK_HALF $end
$var parameter 2 - SHIFT_HIGH $end
$var parameter 2 . SHIFT_LOW $end
$var reg 3 / bit_count [2:0] $end
$var reg 1 $ busy $end
$var reg 4 0 clk_count [3:0] $end
$var reg 1 # cs $end
$var reg 1 " mosi $end
$var reg 1 ! sclk $end
$var reg 8 1 shift_reg [7:0] $end
$var reg 2 2 state [1:0] $end
$upscope $end
$upscope $end
$enddefinitions $end
$comment Show the parameter values. $end
$dumpall
b1 .
b10 -
b100 ,
b0 +
b11 *
$end
#0
$dumpvars
b0 2
b0 1
b0 0
b0 /
b0 )
0(
0'
b0 &
0%
0$
1#
0"
0!
$end
#5000
1%
#10000
0%
#15000
1%
#20000
0%
1'
#25000
1%
#30000
0%
#35000
1%
#40000
0%
1(
b10101010 &
b10101010 )
#45000
1"
b10101010 1
1$
0#
b1 2
1%
#50000
0%
0(
#55000
b1 0
1%
#60000
0%
#65000
b10 0
1%
#70000
0%
#75000
b11 0
1%
#80000
0%
#85000
1!
b0 0
b10 2
1%
#90000
0%
#95000
b1 0
1%
#100000
0%
#105000
b10 0
1%
#110000
0%
#115000
b11 0
1%
#120000
0%
#125000
0"
b1010100 1
b1 /
b1 2
0!
b0 0
1%
#130000
0%
#135000
b1 0
1%
#140000
0%
#145000
b10 0
1%
#150000
0%
#155000
b11 0
1%
#160000
0%
#165000
1!
b0 0
b10 2
1%
#170000
0%
#175000
b1 0
1%
#180000
0%
#185000
b10 0
1%
#190000
0%
#195000
b11 0
1%
#200000
0%
#205000
1"
b10101000 1
b10 /
b1 2
0!
b0 0
1%
#210000
0%
#215000
b1 0
1%
#220000
0%
#225000
b10 0
1%
#230000
0%
#235000
b11 0
1%
#240000
0%
#245000
1!
b0 0
b10 2
1%
#250000
0%
#255000
b1 0
1%
#260000
0%
#265000
b10 0
1%
#270000
0%
#275000
b11 0
1%
#280000
0%
#285000
0"
b1010000 1
b11 /
b1 2
0!
b0 0
1%
#290000
0%
#295000
b1 0
1%
#300000
0%
#305000
b10 0
1%
#310000
0%
#315000
b11 0
1%
#320000
0%
#325000
1!
b0 0
b10 2
1%
#330000
0%
#335000
b1 0
1%
#340000
0%
#345000
b10 0
1%
#350000
0%
#355000
b11 0
1%
#360000
0%
#365000
1"
b10100000 1
b100 /
b1 2
0!
b0 0
1%
#370000
0%
#375000
b1 0
1%
#380000
0%
#385000
b10 0
1%
#390000
0%
#395000
b11 0
1%
#400000
0%
#405000
1!
b0 0
b10 2
1%
#410000
0%
#415000
b1 0
1%
#420000
0%
#425000
b10 0
1%
#430000
0%
#435000
b11 0
1%
#440000
0%
#445000
0"
b1000000 1
b101 /
b1 2
0!
b0 0
1%
#450000
0%
#455000
b1 0
1%
#460000
0%
#465000
b10 0
1%
#470000
0%
#475000
b11 0
1%
#480000
0%
#485000
1!
b0 0
b10 2
1%
#490000
0%
#495000
b1 0
1%
#500000
0%
#505000
b10 0
1%
#510000
0%
#515000
b11 0
1%
#520000
0%
#525000
1"
b10000000 1
b110 /
b1 2
0!
b0 0
1%
#530000
0%
#535000
b1 0
1%
#540000
0%
#545000
b10 0
1%
#550000
0%
#555000
b11 0
1%
#560000
0%
#565000
1!
b0 0
b10 2
1%
#570000
0%
#575000
b1 0
1%
#580000
0%
#585000
b10 0
1%
#590000
0%
#595000
b11 0
1%
#600000
0%
#605000
0"
b0 1
b111 /
b1 2
0!
b0 0
1%
#610000
0%
#615000
b1 0
1%
#620000
0%
#625000
b10 0
1%
#630000
0%
#635000
b11 0
1%
#640000
0%
#645000
1!
b0 0
b10 2
1%
#650000
0%
#655000
b1 0
1%
#660000
0%
#665000
b10 0
1%
#670000
0%
#675000
b11 0
1%
#680000
0%
#685000
b11 2
0!
b0 0
1%
#690000
0%
#695000
b0 2
0$
1#
1%
